Workbook

Sheet Resumen
A1: Resumen de Cuentas Streaming
A3: Cuentas Activas | C3: Por Vencer (≤3 días) | E3: Vencidas | G3: Ingreso Mensual Activo | I3: Ganancia Mensual Activa
A4: =COUNTIF(Cuentas!Q2:Q300,"Activa") | C4: =COUNTIF(Cuentas!Q2:Q300,"Por vencer") | E4: =COUNTIF(Cuentas!Q2:Q300,"Vencida") | G4: =SUMIF(Cuentas!Q2:Q300,"Activa",Cuentas!L2:L300) | I4: =SUMIF(Cuentas!Q2:Q300,"Activa",Cuentas!M2:M300)
A8: Cuentas por Servicio
A9: Servicio | B9: Cantidad | C9: Ingreso Total | D9: Ganancia Total
A10: Netflix | B10: =COUNTIF(Cuentas!A2:A300,A10) | C10: =SUMIF(Cuentas!A2:A300,A10,Cuentas!L2:L300) | D10: =SUMIF(Cuentas!A2:A300,A10,Cuentas!M2:M300)
A11: Disney+ | B11: =COUNTIF(Cuentas!A2:A300,A11) | C11: =SUMIF(Cuentas!A2:A300,A11,Cuentas!L2:L300) | D11: =SUMIF(Cuentas!A2:A300,A11,Cuentas!M2:M300)
A12: HBO Max | B12: =COUNTIF(Cuentas!A2:A300,A12) | C12: =SUMIF(Cuentas!A2:A300,A12,Cuentas!L2:L300) | D12: =SUMIF(Cuentas!A2:A300,A12,Cuentas!M2:M300)
A13: Amazon Prime Video | B13: =COUNTIF(Cuentas!A2:A300,A13) | C13: =SUMIF(Cuentas!A2:A300,A13,Cuentas!L2:L300) | D13: =SUMIF(Cuentas!A2:A300,A13,Cuentas!M2:M300)
A14: Paramount+ | B14: =COUNTIF(Cuentas!A2:A300,A14) | C14: =SUMIF(Cuentas!A2:A300,A14,Cuentas!L2:L300) | D14: =SUMIF(Cuentas!A2:A300,A14,Cuentas!M2:M300)
A15: Apple TV+ | B15: =COUNTIF(Cuentas!A2:A300,A15) | C15: =SUMIF(Cuentas!A2:A300,A15,Cuentas!L2:L300) | D15: =SUMIF(Cuentas!A2:A300,A15,Cuentas!M2:M300)
A16: Spotify | B16: =COUNTIF(Cuentas!A2:A300,A16) | C16: =SUMIF(Cuentas!A2:A300,A16,Cuentas!L2:L300) | D16: =SUMIF(Cuentas!A2:A300,A16,Cuentas!M2:M300)
A17: YouTube Premium | B17: =COUNTIF(Cuentas!A2:A300,A17) | C17: =SUMIF(Cuentas!A2:A300,A17,Cuentas!L2:L300) | D17: =SUMIF(Cuentas!A2:A300,A17,Cuentas!M2:M300)
A18: Crunchyroll | B18: =COUNTIF(Cuentas!A2:A300,A18) | C18: =SUMIF(Cuentas!A2:A300,A18,Cuentas!L2:L300) | D18: =SUMIF(Cuentas!A2:A300,A18,Cuentas!M2:M300)
A19: Otro | B19: =COUNTIF(Cuentas!A2:A300,A19) | C19: =SUMIF(Cuentas!A2:A300,A19,Cuentas!L2:L300) | D19: =SUMIF(Cuentas!A2:A300,A19,Cuentas!M2:M300)

Sheet Precios
A1: Lista de Precios por Servicio
A4: Servicio | B4: Costo ($) | C4: Valor ($) | D4: Ganancia ($) | E4: Tiempo
A5: Netflix | B5: 4000 | C5: 5500 | D5: =IF(AND(B5<>"",C5<>""),C5-B5,"") | E5: 1 mes
A6: Disney+ | B6: 3000 | C6: 4500 | D6: =IF(AND(B6<>"",C6<>""),C6-B6,"") | E6: 3 meses
A7: HBO Max | B7: 3000 | C7: 4500 | D7: =IF(AND(B7<>"",C7<>""),C7-B7,"") | E7: 3 meses
A8: Amazon Prime Video | B8: 3000 | C8: 4500 | D8: =IF(AND(B8<>"",C8<>""),C8-B8,"") | E8: 1 mes
A9: Paramount+ | B9: 3000 | C9: 4000 | D9: =IF(AND(B9<>"",C9<>""),C9-B9,"") | E9: 1 mes
A10: Apple TV+ | B10: 3000 | C10: 4500 | D10: =IF(AND(B10<>"",C10<>""),C10-B10,"") | E10: 1 mes
A11: Spotify | B11: 4000 | C11: 5500 | D11: =IF(AND(B11<>"",C11<>""),C11-B11,"") | E11: 3 meses
A12: YouTube Premium | B12: 3000 | C12: 4500 | D12: =IF(AND(B12<>"",C12<>""),C12-B12,"") | E12: 1 mes
A13: Crunchyroll | B13: 3000 | C13: 4500 | D13: =IF(AND(B13<>"",C13<>""),C13-B13,"") | E13: 3 meses
A14: ChatGpt (GO) | B14: 5000 | C14: 8000 | D14: =IF(AND(B14<>"",C14<>""),C14-B14,"") | E14: 1 mes

Sheet Cuentas
A1: Servicio | B1: Perfil | C1: Usuario / Correo | D1: Contraseña | E1: Cliente | F1: Teléfono Cliente | G1: Usuario Instagram | H1: Fecha de Inicio | I1: Fecha de Vencimiento | J1: Ciclo de Pago | K1: Costo ($) | L1: Valor ($) | M1: Ganancia ($) | N1: Duración (días) | O1: Días Restantes | P1: Próxima Fecha de Pago | Q1: Estado | R1: En línea | S1: Recordatorio WhatsApp | T1: Observaciones
A2: Netflix | B2: Perfil 1 | C2: prueba@gmail.com | D2: 123456 | E2: sebailesito | F2: 56911111111 | H2: 2026-07-09 | I2: 46243 | J2: Mensual | K2: 4000 | L2: 5500 | M2: 1500 | N2: 31 | O2: 30 | P2: 46243 | Q2: Activa
A3: Netflix | B3: perfil 2 | C3: felipe | D3: 1234 | E3: felipe | F3: +321321321312 | H3: 2026-07-11 | I3: 46245 | J3: Mensual | K3: 4000 | L3: 5500 | M3: 1500 | N3: 31 | O3: 32 | P3: 46245 | Q3: Activa
A4: Netflix | B4: perfil 3 | C4: maggie | D4: 1234 | E4: maggi | F4: +131344444 | H4: 2026-07-11 | I4: 46245 | J4: Mensual | K4: 4000 | L4: 5500 | M4: 1500 | N4: 31 | O4: 32 | P4: 46245 | Q4: Activa
A5: Netflix | B5: perfil 4 | C5: mauro | D5: 1234 | E5: mauro | F5: +1233333333 | G5: mauroperezf | H5: 2026-07-12 | I5: 46246 | J5: Mensual | K5: 4000 | L5: 5500 | M5: 1500 | N5: 31 | O5: 33 | P5: 46246 | Q5: Activa
K6: =IFERROR(VLOOKUP(A6,Precios!$A$5:$C$14,2,FALSE()),"") | L6: =IFERROR(VLOOKUP(A6,Precios!$A$5:$C$14,3,FALSE()),"") | M6: =IF(AND(K6<>"",L6<>""),L6-K6,"") | N6: =IF(AND(H6<>"",I6<>""),I6-H6,"") | O6: =IF(I6<>"",I6-TODAY(),"") | P6: =IF(I6="","",IF(J6="Anual",I6+365,I6+30)) | Q6: =IF(I6="","",IF(O6<0,"Vencida",IF(O6<=3,"Por vencer","Activa"))) | S6: =IF(OR(E6="",I6=""),"",HYPERLINK(IF(F6<>"","https://wa.me/"&SUBSTITUTE(SUBSTITUTE(SUBSTITUTE(F6,"+",""),"-","")," ","")&"?text="&SUBSTITUTE(SUBSTITUTE("Hola "&E6&", tu cuenta de "&A6&" vence el "&TEXT(I6,"dd/mm/yyyy")&". Deseas renovarla?"," ","%20"),"?","%3F"),"https://api.whatsapp.com/send?text="&SUBSTITUTE(SUBSTITUTE("Hola "&E6&", tu cuenta de "&A6&" vence el "&TEXT(I6,"dd/mm/yyyy")&". Deseas renovarla?"," ","%20"),"?","%3F")),"Enviar recordatorio"))
K7: =IFERROR(VLOOKUP(A7,Precios!$A$5:$C$14,2,FALSE()),"") | L7: =IFERROR(VLOOKUP(A7,Precios!$A$5:$C$14,3,FALSE()),"") | M7: =IF(AND(K7<>"",L7<>""),L7-K7,"") | N7: =IF(AND(H7<>"",I7<>""),I7-H7,"") | O7: =IF(I7<>"",I7-TODAY(),"") | P7: =IF(I7="","",IF(J7="Anual",I7+365,I7+30)) | Q7: =IF(I7="","",IF(O7<0,"Vencida",IF(O7<=3,"Por vencer","Activa"))) | S7: =IF(OR(E7="",I7=""),"",HYPERLINK(IF(F7<>"","https://wa.me/"&SUBSTITUTE(SUBSTITUTE(SUBSTITUTE(F7,"+",""),"-","")," ","")&"?text="&SUBSTITUTE(SUBSTITUTE("Hola "&E7&", tu cuenta de "&A7&" vence el "&TEXT(I7,"dd/mm/yyyy")&". Deseas renovarla?"," ","%20"),"?","%3F"),"https://api.whatsapp.com/send?text="&SUBSTITUTE(SUBSTITUTE("Hola "&E7&", tu cuenta de "&A7&" vence el "&TEXT(I7,"dd/mm/yyyy")&". Deseas renovarla?"," ","%20"),"?","%3F")),"Enviar recordatorio"))
K8: =IFERROR(VLOOKUP(A8,Precios!$A$5:$C$14,2,FALSE()),"") | L8: =IFERROR(VLOOKUP(A8,Precios!$A$5:$C$14,3,FALSE()),"") | M8: =IF(AND(K8<>"",L8<>""),L8-K8,"") | N8: =IF(AND(H8<>"",I8<>""),I8-H8,"") | O8: =IF(I8<>"",I8-TODAY(),"") | P8: =IF(I8="","",IF(J8="Anual",I8+365,I8+30)) | Q8: =IF(I8="","",IF(O8<0,"Vencida",IF(O8<=3,"Por vencer","Activa"))) | S8: =IF(OR(E8="",I8=""),"",HYPERLINK(IF(F8<>"","https://wa.me/"&SUBSTITUTE(SUBSTITUTE(SUBSTITUTE(F8,"+",""),"-","")," ","")&"?text="&SUBSTITUTE(SUBSTITUTE("Hola "&E8&", tu cuenta de "&A8&" vence el "&TEXT(I8,"dd/mm/yyyy")&". Deseas renovarla?"," ","%20"),"?","%3F"),"https://api.whatsapp.com/send?text="&SUBSTITUTE(SUBSTITUTE("Hola "&E8&", tu cuenta de "&A8&" vence el "&TEXT(I8,"dd/mm/yyyy")&". Deseas renovarla?"," ","%20"),"?","%3F")),"Enviar recordatorio"))
K9: =IFERROR(VLOOKUP(A9,Precios!$A$5:$C$14,2,FALSE()),"") | L9: =IFERROR(VLOOKUP(A9,Precios!$A$5:$C$14,3,FALSE()),"") | M9: =IF(AND(K9<>"",L9<>""),L9-K9,"") | N9: =IF(AND(H9<>"",I9<>""),I9-H9,"") | O9: =IF(I9<>"",I9-TODAY(),"") | P9: =IF(I9="","",IF(J9="Anual",I9+365,I9+30)) | Q9: =IF(I9="","",IF(O9<0,"Vencida",IF(O9<=3,"Por vencer","Activa"))) | S9: =IF(OR(E9="",I9=""),"",HYPERLINK(IF(F9<>"","https://wa.me/"&SUBSTITUTE(SUBSTITUTE(SUBSTITUTE(F9,"+",""),"-","")," ","")&"?text="&SUBSTITUTE(SUBSTITUTE("Hola "&E9&", tu cuenta de "&A9&" vence el "&TEXT(I9,"dd/mm/yyyy")&". Deseas renovarla?"," ","%20"),"?","%3F"),"https://api.whatsapp.com/send?text="&SUBSTITUTE(SUBSTITUTE("Hola "&E9&", tu cuenta de "&A9&" vence el "&TEXT(I9,"dd/mm/yyyy")&". Deseas renovarla?"," ","%20"),"?","%3F")),"Enviar recordatorio"))
K10: =IFERROR(VLOOKUP(A10,Precios!$A$5:$C$14,2,FALSE()),"") | L10: =IFERROR(VLOOKUP(A10,Precios!$A$5:$C$14,3,FALSE()),"") | M10: =IF(AND(K10<>"",L10<>""),L10-K10,"") | N10: =IF(AND(H10<>"",I10<>""),I10-H10,"") | O10: =IF(I10<>"",I10-TODAY(),"") | P10: =IF(I10="","",IF(J10="Anual",I10+365,I10+30)) | Q10: =IF(I10="","",IF(O10<0,"Vencida",IF(O10<=3,"Por vencer","Activa"))) | S10: =IF(OR(E10="",I10=""),"",HYPERLINK(IF(F10<>"","https://wa.me/"&SUBSTITUTE(SUBSTITUTE(SUBSTITUTE(F10,"+",""),"-","")," ","")&"?text="&SUBSTITUTE(SUBSTITUTE("Hola "&E10&", tu cuenta de "&A10&" vence el "&TEXT(I10,"dd/mm/yyyy")&". Deseas renovarla?"," ","%20"),"?","%3F"),"https://api.whatsapp.com/send?text="&SUBSTITUTE(SUBSTITUTE("Hola "&E10&", tu cuenta de "&A10&" vence el "&TEXT(I10,"dd/mm/yyyy")&". Deseas renovarla?"," ","%20"),"?","%3F")),"Enviar recordatorio"))
K11: =IFERROR(VLOOKUP(A11,Precios!$A$5:$C$14,2,FALSE()),"") | L11: =IFERROR(VLOOKUP(A11,Precios!$A$5:$C$14,3,FALSE()),"") | M11: =IF(AND(K11<>"",L11<>""),L11-K11,"") | N11: =IF(AND(H11<>"",I11<>""),I11-H11,"") | O11: =IF(I11<>"",I11-TODAY(),"") | P11: =IF(I11="","",IF(J11="Anual",I11+365,I11+30)) | Q11: =IF(I11="","",IF(O11<0,"Vencida",IF(O11<=3,"Por vencer","Activa"))) | S11: =IF(OR(E11="",I11=""),"",HYPERLINK(IF(F11<>"","https://wa.me/"&SUBSTITUTE(SUBSTITUTE(SUBSTITUTE(F11,"+",""),"-","")," ","")&"?text="&SUBSTITUTE(SUBSTITUTE("Hola "&E11&", tu cuenta de "&A11&" vence el "&TEXT(I11,"dd/mm/yyyy")&". Deseas renovarla?"," ","%20"),"?","%3F"),"https://api.whatsapp.com/send?text="&SUBSTITUTE(SUBSTITUTE("Hola "&E11&", tu cuenta de "&A11&" vence el "&TEXT(I11,"dd/mm/yyyy")&". Deseas renovarla?"," ","%20"),"?","%3F")),"Enviar recordatorio"))
K12: =IFERROR(VLOOKUP(A12,Precios!$A$5:$C$14,2,FALSE()),"") | L12: =IFERROR(VLOOKUP(A12,Precios!$A$5:$C$14,3,FALSE()),"") | M12: =IF(AND(K12<>"",L12<>""),L12-K12,"") | N12: =IF(AND(H12<>"",I12<>""),I12-H12,"") | O12: =IF(I12<>"",I12-TODAY(),"") | P12: =IF(I12="","",IF(J12="Anual",I12+365,I12+30)) | Q12: =IF(I12="","",IF(O12<0,"Vencida",IF(O12<=3,"Por vencer","Activa"))) | S12: =IF(OR(E12="",I12=""),"",HYPERLINK(IF(F12<>"","https://wa.me/"&SUBSTITUTE(SUBSTITUTE(SUBSTITUTE(F12,"+",""),"-","")," ","")&"?text="&SUBSTITUTE(SUBSTITUTE("Hola "&E12&", tu cuenta de "&A12&" vence el "&TEXT(I12,"dd/mm/yyyy")&". Deseas renovarla?"," ","%20"),"?","%3F"),"https://api.whatsapp.com/send?text="&SUBSTITUTE(SUBSTITUTE("Hola "&E12&", tu cuenta de "&A12&" vence el "&TEXT(I12,"dd/mm/yyyy")&". Deseas renovarla?"," ","%20"),"?","%3F")),"Enviar recordatorio"))
K13: =IFERROR(VLOOKUP(A13,Precios!$A$5:$C$14,2,FALSE()),"") | L13: =IFERROR(VLOOKUP(A13,Precios!$A$5:$C$14,3,FALSE()),"") | M13: =IF(AND(K13<>"",L13<>""),L13-K13,"") | N13: =IF(AND(H13<>"",I13<>""),I13-H13,"") | O13: =IF(I13<>"",I13-TODAY(),"") | P13: =IF(I13="","",IF(J13="Anual",I13+365,I13+30)) | Q13: =IF(I13="","",IF(O13<0,"Vencida",IF(O13<=3,"Por vencer","Activa"))) | S13: =IF(OR(E13="",I13=""),"",HYPERLINK(IF(F13<>"","https://wa.me/"&SUBSTITUTE(SUBSTITUTE(SUBSTITUTE(F13,"+",""),"-","")," ","")&"?text="&SUBSTITUTE(SUBSTITUTE("Hola "&E13&", tu cuenta de "&A13&" vence el "&TEXT(I13,"dd/mm/yyyy")&". Deseas renovarla?"," ","%20"),"?","%3F"),"https://api.whatsapp.com/send?text="&SUBSTITUTE(SUBSTITUTE("Hola "&E13&", tu cuenta de "&A13&" vence el "&TEXT(I13,"dd/mm/yyyy")&". Deseas renovarla?"," ","%20"),"?","%3F")),"Enviar recordatorio"))
K14: =IFERROR(VLOOKUP(A14,Precios!$A$5:$C$14,2,FALSE()),"") | L14: =IFERROR(VLOOKUP(A14,Precios!$A$5:$C$14,3,FALSE()),"") | M14: =IF(AND(K14<>"",L14<>""),L14-K14,"") | N14: =IF(AND(H14<>"",I14<>""),I14-H14,"") | O14: =IF(I14<>"",I14-TODAY(),"") | P14: =IF(I14="","",IF(J14="Anual",I14+365,I14+30)) | Q14: =IF(I14="","",IF(O14<0,"Vencida",IF(O14<=3,"Por vencer","Activa"))) | S14: =IF(OR(E14="",I14=""),"",HYPERLINK(IF(F14<>"","https://wa.me/"&SUBSTITUTE(SUBSTITUTE(SUBSTITUTE(F14,"+",""),"-","")," ","")&"?text="&SUBSTITUTE(SUBSTITUTE("Hola "&E14&", tu cuenta de "&A14&" vence el "&TEXT(I14,"dd/mm/yyyy")&". Deseas renovarla?"," ","%20"),"?","%3F"),"https://api.whatsapp.com/send?text="&SUBSTITUTE(SUBSTITUTE("Hola "&E14&", tu cuenta de "&A14&" vence el "&TEXT(I14,"dd/mm/yyyy")&". Deseas renovarla?"," ","%20"),"?","%3F")),"Enviar recordatorio"))
K15: =IFERROR(VLOOKUP(A15,Precios!$A$5:$C$14,2,FALSE()),"") | L15: =IFERROR(VLOOKUP(A15,Precios!$A$5:$C$14,3,FALSE()),"") | M15: =IF(AND(K15<>"",L15<>""),L15-K15,"") | N15: =IF(AND(H15<>"",I15<>""),I15-H15,"") | O15: =IF(I15<>"",I15-TODAY(),"") | P15: =IF(I15="","",IF(J15="Anual",I15+365,I15+30)) | Q15: =IF(I15="","",IF(O15<0,"Vencida",IF(O15<=3,"Por vencer","Activa"))) | S15: =IF(OR(E15="",I15=""),"",HYPERLINK(IF(F15<>"","https://wa.me/"&SUBSTITUTE(SUBSTITUTE(SUBSTITUTE(F15,"+",""),"-","")," ","")&"?text="&SUBSTITUTE(SUBSTITUTE("Hola "&E15&", tu cuenta de "&A15&" vence el "&TEXT(I15,"dd/mm/yyyy")&". Deseas renovarla?"," ","%20"),"?","%3F"),"https://api.whatsapp.com/send?text="&SUBSTITUTE(SUBSTITUTE("Hola "&E15&", tu cuenta de "&A15&" vence el "&TEXT(I15,"dd/mm/yyyy")&". Deseas renovarla?"," ","%20"),"?","%3F")),"Enviar recordatorio"))
K16: =IFERROR(VLOOKUP(A16,Precios!$A$5:$C$14,2,FALSE()),"") | L16: =IFERROR(VLOOKUP(A16,Precios!$A$5:$C$14,3,FALSE()),"") | M16: =IF(AND(K16<>"",L16<>""),L16-K16,"") | N16: =IF(AND(H16<>"",I16<>""),I16-H16,"") | O16: =IF(I16<>"",I16-TODAY(),"") | P16: =IF(I16="","",IF(J16="Anual",I16+365,I16+30)) | Q16: =IF(I16="","",IF(O16<0,"Vencida",IF(O16<=3,"Por vencer","Activa"))) | S16: =IF(OR(E16="",I16=""),"",HYPERLINK(IF(F16<>"","https://wa.me/"&SUBSTITUTE(SUBSTITUTE(SUBSTITUTE(F16,"+",""),"-","")," ","")&"?text="&SUBSTITUTE(SUBSTITUTE("Hola "&E16&", tu cuenta de "&A16&" vence el "&TEXT(I16,"dd/mm/yyyy")&". Deseas renovarla?"," ","%20"),"?","%3F"),"https://api.whatsapp.com/send?text="&SUBSTITUTE(SUBSTITUTE("Hola "&E16&", tu cuenta de "&A16&" vence el "&TEXT(I16,"dd/mm/yyyy")&". Deseas renovarla?"," ","%20"),"?","%3F")),"Enviar recordatorio"))
K17: =IFERROR(VLOOKUP(A17,Precios!$A$5:$C$14,2,FALSE()),"") | L17: =IFERROR(VLOOKUP(A17,Precios!$A$5:$C$14,3,FALSE()),"") | M17: =IF(AND(K17<>"",L17<>""),L17-K17,"") | N17: =IF(AND(H17<>"",I17<>""),I17-H17,"") | O17: =IF(I17<>"",I17-TODAY(),"") | P17: =IF(I17="","",IF(J17="Anual",I17+365,I17+30)) | Q17: =IF(I17="","",IF(O17<0,"Vencida",IF(O17<=3,"Por vencer","Activa"))) | S17: =IF(OR(E17="",I17=""),"",HYPERLINK(IF(F17<>"","https://wa.me/"&SUBSTITUTE(SUBSTITUTE(SUBSTITUTE(F17,"+",""),"-","")," ","")&"?text="&SUBSTITUTE(SUBSTITUTE("Hola "&E17&", tu cuenta de "&A17&" vence el "&TEXT(I17,"dd/mm/yyyy")&". Deseas renovarla?"," ","%20"),"?","%3F"),"https://api.whatsapp.com/send?text="&SUBSTITUTE(SUBSTITUTE("Hola "&E17&", tu cuenta de "&A17&" vence el "&TEXT(I17,"dd/mm/yyyy")&". Deseas renovarla?"," ","%20"),"?","%3F")),"Enviar recordatorio"))
... K300: =IFERROR(VLOOKUP(A300,Precios!$A$5:$C$14,2,FALSE()),"") | L300: =IFERROR(VLOOKUP(A300,Precios!$A$5:$C$14,3,FALSE()),"") | M300: =IF(AND(K300<>"",L300<>""),L300-K300,"") | N300: =IF(AND(H300<>"",I300<>""),I300-H300,"") | O300: =IF(I300<>"",I300-TODAY(),"") | P300: =IF(I300="","",IF(J300="Anual",I300+365,I300+30)) | Q300: =IF(I300="","",IF(O300<0,"Vencida",IF(O300<=3,"Por vencer","Activa"))) | S300: =IF(OR(E300="",I300=""),"",HYPERLINK(IF(F300<>"","https://wa.me/"&SUBSTITUTE(SUBSTITUTE(SUBSTITUTE(F300,"+",""),"-","")," ","")&"?text="&SUBSTITUTE(SUBSTITUTE("Hola "&E300&", tu cuenta de "&A300&" vence el "&TEXT(I300,"dd/mm/yyyy")&". Deseas renovarla?"," ","%20"),"?","%3F"),"https://api.whatsapp.com/send?text="&SUBSTITUTE(SUBSTITUTE("Hola "&E300&", tu cuenta de "&A300&" vence el "&TEXT(I300,"dd/mm/yyyy")&". Deseas renovarla?"," ","%20"),"?","%3F")),"Enviar recordatorio"))

Sheet Clientes
A1: Resumen por Cliente
A3: Cliente | B3: Usuario Instagram (opcional) | C3: Teléfono (opcional) | D3: Cantidad de Cuentas | E3: Gasto Mensual Total | F3: Próximo Vencimiento | G3: Estado General
C7: =IF(A7="","",IFERROR(VLOOKUP(A7,Cuentas!$E$2:$F$300,2,FALSE()),"")) | D7: =IF(A7="","",COUNTIF(Cuentas!$E$2:$E$300,A7)) | E7: =IF(A7="","",SUMIF(Cuentas!$E$2:$E$300,A7,Cuentas!$L$2:$L$300)) | F7: =IF(OR(A7="",D7=0),"",SUMPRODUCT(MIN(IF(Cuentas!$E$2:$E$300=A7,IF(Cuentas!$I$2:$I$300<>"",Cuentas!$I$2:$I$300))))) | G7: =IF(OR(A7="",D7=0),"",IF(COUNTIFS(Cuentas!$E$2:$E$300,A7,Cuentas!$Q$2:$Q$300,"Vencida")>0,"Tiene cuentas vencidas","Al día"))
C8: =IF(A8="","",IFERROR(VLOOKUP(A8,Cuentas!$E$2:$F$300,2,FALSE()),"")) | D8: =IF(A8="","",COUNTIF(Cuentas!$E$2:$E$300,A8)) | E8: =IF(A8="","",SUMIF(Cuentas!$E$2:$E$300,A8,Cuentas!$L$2:$L$300)) | F8: =IF(OR(A8="",D8=0),"",SUMPRODUCT(MIN(IF(Cuentas!$E$2:$E$300=A8,IF(Cuentas!$I$2:$I$300<>"",Cuentas!$I$2:$I$300))))) | G8: =IF(OR(A8="",D8=0),"",IF(COUNTIFS(Cuentas!$E$2:$E$300,A8,Cuentas!$Q$2:$Q$300,"Vencida")>0,"Tiene cuentas vencidas","Al día"))
C9: =IF(A9="","",IFERROR(VLOOKUP(A9,Cuentas!$E$2:$F$300,2,FALSE()),"")) | D9: =IF(A9="","",COUNTIF(Cuentas!$E$2:$E$300,A9)) | E9: =IF(A9="","",SUMIF(Cuentas!$E$2:$E$300,A9,Cuentas!$L$2:$L$300)) | F9: =IF(OR(A9="",D9=0),"",SUMPRODUCT(MIN(IF(Cuentas!$E$2:$E$300=A9,IF(Cuentas!$I$2:$I$300<>"",Cuentas!$I$2:$I$300))))) | G9: =IF(OR(A9="",D9=0),"",IF(COUNTIFS(Cuentas!$E$2:$E$300,A9,Cuentas!$Q$2:$Q$300,"Vencida")>0,"Tiene cuentas vencidas","Al día"))
C10: =IF(A10="","",IFERROR(VLOOKUP(A10,Cuentas!$E$2:$F$300,2,FALSE()),"")) | D10: =IF(A10="","",COUNTIF(Cuentas!$E$2:$E$300,A10)) | E10: =IF(A10="","",SUMIF(Cuentas!$E$2:$E$300,A10,Cuentas!$L$2:$L$300)) | F10: =IF(OR(A10="",D10=0),"",SUMPRODUCT(MIN(IF(Cuentas!$E$2:$E$300=A10,IF(Cuentas!$I$2:$I$300<>"",Cuentas!$I$2:$I$300))))) | G10: =IF(OR(A10="",D10=0),"",IF(COUNTIFS(Cuentas!$E$2:$E$300,A10,Cuentas!$Q$2:$Q$300,"Vencida")>0,"Tiene cuentas vencidas","Al día"))
C11: =IF(A11="","",IFERROR(VLOOKUP(A11,Cuentas!$E$2:$F$300,2,FALSE()),"")) | D11: =IF(A11="","",COUNTIF(Cuentas!$E$2:$E$300,A11)) | E11: =IF(A11="","",SUMIF(Cuentas!$E$2:$E$300,A11,Cuentas!$L$2:$L$300)) | F11: =IF(OR(A11="",D11=0),"",SUMPRODUCT(MIN(IF(Cuentas!$E$2:$E$300=A11,IF(Cuentas!$I$2:$I$300<>"",Cuentas!$I$2:$I$300))))) | G11: =IF(OR(A11="",D11=0),"",IF(COUNTIFS(Cuentas!$E$2:$E$300,A11,Cuentas!$Q$2:$Q$300,"Vencida")>0,"Tiene cuentas vencidas","Al día"))
C12: =IF(A12="","",IFERROR(VLOOKUP(A12,Cuentas!$E$2:$F$300,2,FALSE()),"")) | D12: =IF(A12="","",COUNTIF(Cuentas!$E$2:$E$300,A12)) | E12: =IF(A12="","",SUMIF(Cuentas!$E$2:$E$300,A12,Cuentas!$L$2:$L$300)) | F12: =IF(OR(A12="",D12=0),"",SUMPRODUCT(MIN(IF(Cuentas!$E$2:$E$300=A12,IF(Cuentas!$I$2:$I$300<>"",Cuentas!$I$2:$I$300))))) | G12: =IF(OR(A12="",D12=0),"",IF(COUNTIFS(Cuentas!$E$2:$E$300,A12,Cuentas!$Q$2:$Q$300,"Vencida")>0,"Tiene cuentas vencidas","Al día"))
C13: =IF(A13="","",IFERROR(VLOOKUP(A13,Cuentas!$E$2:$F$300,2,FALSE()),"")) | D13: =IF(A13="","",COUNTIF(Cuentas!$E$2:$E$300,A13)) | E13: =IF(A13="","",SUMIF(Cuentas!$E$2:$E$300,A13,Cuentas!$L$2:$L$300)) | F13: =IF(OR(A13="",D13=0),"",SUMPRODUCT(MIN(IF(Cuentas!$E$2:$E$300=A13,IF(Cuentas!$I$2:$I$300<>"",Cuentas!$I$2:$I$300))))) | G13: =IF(OR(A13="",D13=0),"",IF(COUNTIFS(Cuentas!$E$2:$E$300,A13,Cuentas!$Q$2:$Q$300,"Vencida")>0,"Tiene cuentas vencidas","Al día"))
C14: =IF(A14="","",IFERROR(VLOOKUP(A14,Cuentas!$E$2:$F$300,2,FALSE()),"")) | D14: =IF(A14="","",COUNTIF(Cuentas!$E$2:$E$300,A14)) | E14: =IF(A14="","",SUMIF(Cuentas!$E$2:$E$300,A14,Cuentas!$L$2:$L$300)) | F14: =IF(OR(A14="",D14=0),"",SUMPRODUCT(MIN(IF(Cuentas!$E$2:$E$300=A14,IF(Cuentas!$I$2:$I$300<>"",Cuentas!$I$2:$I$300))))) | G14: =IF(OR(A14="",D14=0),"",IF(COUNTIFS(Cuentas!$E$2:$E$300,A14,Cuentas!$Q$2:$Q$300,"Vencida")>0,"Tiene cuentas vencidas","Al día"))
C15: =IF(A15="","",IFERROR(VLOOKUP(A15,Cuentas!$E$2:$F$300,2,FALSE()),"")) | D15: =IF(A15="","",COUNTIF(Cuentas!$E$2:$E$300,A15)) | E15: =IF(A15="","",SUMIF(Cuentas!$E$2:$E$300,A15,Cuentas!$L$2:$L$300)) | F15: =IF(OR(A15="",D15=0),"",SUMPRODUCT(MIN(IF(Cuentas!$E$2:$E$300=A15,IF(Cuentas!$I$2:$I$300<>"",Cuentas!$I$2:$I$300))))) | G15: =IF(OR(A15="",D15=0),"",IF(COUNTIFS(Cuentas!$E$2:$E$300,A15,Cuentas!$Q$2:$Q$300,"Vencida")>0,"Tiene cuentas vencidas","Al día"))
C16: =IF(A16="","",IFERROR(VLOOKUP(A16,Cuentas!$E$2:$F$300,2,FALSE()),"")) | D16: =IF(A16="","",COUNTIF(Cuentas!$E$2:$E$300,A16)) | E16: =IF(A16="","",SUMIF(Cuentas!$E$2:$E$300,A16,Cuentas!$L$2:$L$300)) | F16: =IF(OR(A16="",D16=0),"",SUMPRODUCT(MIN(IF(Cuentas!$E$2:$E$300=A16,IF(Cuentas!$I$2:$I$300<>"",Cuentas!$I$2:$I$300))))) | G16: =IF(OR(A16="",D16=0),"",IF(COUNTIFS(Cuentas!$E$2:$E$300,A16,Cuentas!$Q$2:$Q$300,"Vencida")>0,"Tiene cuentas vencidas","Al día"))
C17: =IF(A17="","",IFERROR(VLOOKUP(A17,Cuentas!$E$2:$F$300,2,FALSE()),"")) | D17: =IF(A17="","",COUNTIF(Cuentas!$E$2:$E$300,A17)) | E17: =IF(A17="","",SUMIF(Cuentas!$E$2:$E$300,A17,Cuentas!$L$2:$L$300)) | F17: =IF(OR(A17="",D17=0),"",SUMPRODUCT(MIN(IF(Cuentas!$E$2:$E$300=A17,IF(Cuentas!$I$2:$I$300<>"",Cuentas!$I$2:$I$300))))) | G17: =IF(OR(A17="",D17=0),"",IF(COUNTIFS(Cuentas!$E$2:$E$300,A17,Cuentas!$Q$2:$Q$300,"Vencida")>0,"Tiene cuentas vencidas","Al día"))
C18: =IF(A18="","",IFERROR(VLOOKUP(A18,Cuentas!$E$2:$F$300,2,FALSE()),"")) | D18: =IF(A18="","",COUNTIF(Cuentas!$E$2:$E$300,A18)) | E18: =IF(A18="","",SUMIF(Cuentas!$E$2:$E$300,A18,Cuentas!$L$2:$L$300)) | F18: =IF(OR(A18="",D18=0),"",SUMPRODUCT(MIN(IF(Cuentas!$E$2:$E$300=A18,IF(Cuentas!$I$2:$I$300<>"",Cuentas!$I$2:$I$300))))) | G18: =IF(OR(A18="",D18=0),"",IF(COUNTIFS(Cuentas!$E$2:$E$300,A18,Cuentas!$Q$2:$Q$300,"Vencida")>0,"Tiene cuentas vencidas","Al día"))
... C63: =IF(A63="","",IFERROR(VLOOKUP(A63,Cuentas!$E$2:$F$300,2,FALSE()),"")) | D63: =IF(A63="","",COUNTIF(Cuentas!$E$2:$E$300,A63)) | E63: =IF(A63="","",SUMIF(Cuentas!$E$2:$E$300,A63,Cuentas!$L$2:$L$300)) | F63: =IF(OR(A63="",D63=0),"",SUMPRODUCT(MIN(IF(Cuentas!$E$2:$E$300=A63,IF(Cuentas!$I$2:$I$300<>"",Cuentas!$I$2:$I$300))))) | G63: =IF(OR(A63="",D63=0),"",IF(COUNTIFS(Cuentas!$E$2:$E$300,A63,Cuentas!$Q$2:$Q$300,"Vencida")>0,"Tiene cuentas vencidas","Al día"))
